README.rst
setup.cfg
setup.py
aioesl/__init__.py
aioesl/helpers.py
aioesl/log.py
aioesl/protocol.py
aioesl.egg-info/PKG-INFO
aioesl.egg-info/SOURCES.txt
aioesl.egg-info/dependency_links.txt
aioesl.egg-info/not-zip-safe
aioesl.egg-info/top_level.txt