Metadata-Version: 1.0
Name: aioesl
Version: 0.1.3.3
Summary: asyncio based protocol for the FreeSWITCH's Event Socket
Home-page: https://github.com/runtel/aioesl
Author: Alexey Panyovin
Author-email: a@runtel.ru
License: BSD
Platform: UNKNOWN
